Workbook

Sheet Cover
A1: Sandisk Corporation (SNDK)
A2: Technology · Standard (forward multiples + DCF) · generated 2026-10-13 · data: Yahoo snapshot as of 2026-07-09
A4: Current price | B4: =Assumptions!$B$5
A5: DCF value per share (one lens) | B5: =DCF!$B$24
A6: Upside / downside | B6: =DCF!$B$24/Assumptions!$B$5-1
A7: 12-month price target (report) | B7: 1221.648
A8: WACC | B8: =WACC!$B$10
A10: How to use
A11: Blue cells are inputs — edit growth, margins, beta, ERP or terminal g
A12: in the Assumptions sheet and everything recalculates live.
A13: Black cells are formulas; green cells link across sheets.
A14: The Sensitivity grid re-runs the full DCF per WACC/g pair.
A15: Not investment advice. Verify source data before relying on outputs.

Sheet Target Price
A1: SNDK — 12-month price target (lens triangulation)
A2: Blue = inputs (weights, Ke, dividends, Street weight); black = live formulas. Change a weight and the blended fair value and target recalculate. Guardrail exclusions are already reflected in the effective weights.
A4: Lens | B4: Type | C4: Value / share | D4: Low | E4: High | F4: Weight | G4: Status
A5: Discounted cash flow (FCFF) | B5: intrinsic | C5: 537.1709 | D5: 430.75732 | E5: 659.70982 | F5: 0.38888889 | G5: ok
A6: Forward P/E | B6: relative | C6: 1387.8211 | D6: 1138.0133 | E6: 1637.6289 | F6: 0.33333333 | G6: ok
A7: Forward EV/EBITDA | B7: relative | C7: 1164.9125 | D7: 954.54636 | E7: 1375.2786 | F7: 0.27777778 | G7: ok
A9: Weights sum | B9: =SUM(F5:F7)
A10: Blended fair value (today) | B10: =SUMPRODUCT(C5:C7,F5:F7)/SUM(F5:F7)
A11: Cost of equity (Ke) | B11: 0.093902974
A12: Dividends per share (12m) | B12: 0
A13: Model 12-month target = FV×(1+Ke)−DPS | B13: =$B$10*(1+$B$11)-$B$12
A14: Street mean target | B14: 1975.95
A15: Street weight in target | B15: 0.15
A16: Published 12-month target | B16: =(1-$B$15)*$B$13+$B$15*$B$14
A17: Current price | B17: 1727.18
A18: Engine target (incl. plausibility band) | B18: 1221.648
A20: Guardrails
A21: Target anchored 15% to the Street consensus ($1,975.95); model-only target $1,088.54.

Sheet Financial Model
A1: SNDK — projected P&L & levered FCF (DCF base case)
A2: Blue = consensus-sourced figures; black = live formulas. Revenue and EBIT margin are the DCF base-case drivers; levered FCF = unlevered FCF less after-tax interest.
A4: Line item | B4: FY2026E | C4: FY2027E | D4: FY2028E | E4: FY2029E | F4: FY2030E | G4: FY2031E | H4: FY2032E | I4: FY2033E | J4: FY2034E | K4: FY2035E
A5: Revenue (mn) | B5: 19770 | C5: 48130 | D5: 53863.538 | E5: 59233.446 | F5: 64080.056 | G5: 68287.465 | H5: 71798.026 | I5: 74625.073 | J5: 76869.969 | K5: 78791.718
A6: Revenue growth | B6: — | C6: =C5/B5-1 | D6: =D5/C5-1 | E6: =E5/D5-1 | F6: =F5/E5-1 | G6: =G5/F5-1 | H6: =H5/G5-1 | I6: =I5/H5-1 | J6: =J5/I5-1 | K6: =K5/J5-1
A7: EBIT margin | B7: 0.35 | C7: 0.35 | D7: 0.30798375 | E7: 0.26596751 | F7: 0.22395126 | G7: 0.18193501 | H7: 0.13991877 | I7: 0.097902522 | J7: 0.097902522 | K7: 0.097902522
A8: EBIT (mn) | B8: =B5*B7 | C8: =C5*C7 | D8: =D5*D7 | E8: =E5*E7 | F8: =F5*F7 | G8: =G5*G7 | H8: =H5*H7 | I8: =I5*I7 | ... K8: =K5*K7
A9: Net income (mn) | B9: 9834.6408 | C9: 30279.913 | D9: 12394.571 | E9: 11768.379 | F9: 10715.857 | G9: 9270.6608 | H9: 7487.1685 | I9: 5432.2371 | J9: 5597.0729 | K9: 5738.181
A10: EPS | B10: =B9*1000000/148089758.0 | C10: =C9*1000000/148089758.0 | D10: =D9*1000000/148089758.0 | E10: =E9*1000000/148089758.0 | F10: =F9*1000000/148089758.0 | G10: =G9*1000000/148089758.0 | H10: =H9*1000000/148089758.0 | I10: =I9*1000000/148089758.0 | ... K10: =K9*1000000/148089758.0
A12: Levered FCF (mn) | B12: 3560.5522 | C12: 8918.0775 | D12: 12057.545 | E12: 11419.345 | F12: 10354.308 | G12: 8892.2649 | H12: 7082.6314 | I12: 4985.8369 | J12: 5083.8103 | K12: 5111.9169
A13: FCF margin | B13: =B12/B5 | C13: =C12/C5 | D13: =D12/D5 | E13: =E12/E5 | F13: =F12/F5 | G13: =G12/G5 | H13: =H12/H5 | I13: =I12/I5 | ... K13: =K12/K5
A15: → Unlevered FCF (before interest) is what the 'DCF' sheet discounts.

Sheet Assumptions
A1: SNDK — Assumptions & Drivers
A2: Blue cells are inputs — change them and the whole model recalculates. Source: Yahoo snapshot as of 2026-07-09, retrieved 2026-10-13.
A4: Market data
A5: Share price (USD) | B5: 1727.18
A6: Diluted shares (mn) | B6: 148.08976
A7: Total debt (USDmm) | B7: 2042
A8: Cash & ST investments (USDmm) | B8: 1481
A9: Minority interest (USDmm) | B9: 0
A10: Net debt (USDmm) | B10: =Assumptions!$B$7-Assumptions!$B$8
A12: Cost of capital inputs
A13: Risk-free rate (Rf) | B13: 0.043
A14: Equity risk premium (ERP) | B14: 0.046
A15: Country risk premium | B15: 0
A16: Size premium | B16: 0
A17: Beta (levered) | B17: 1.11
A18: Pre-tax cost of debt | B18: 0.051
A19: Tax rate | B19: 0.25
A21: Terminal assumptions
A22: Terminal growth (g) | B22: 0.025
A24: Per-year forecast drivers
A25: Driver | B25: FY2026E | C25: FY2027E | D25: FY2028E | E25: FY2029E | F25: FY2030E | G25: FY2031E | H25: FY2032E | I25: FY2033E | J25: FY2034E | K25: FY2035E
A26: Revenue growth | B26: 1.6879674 | C26: 1.4344967 | D26: 0.11912607 | E26: 0.099694691 | F26: 0.081822177 | G26: 0.06565864 | H26: 0.051408561 | I26: 0.039375 | J26: 0.03008233 | K26: 0.025
A27: EBIT margin | B27: 0.35 | C27: 0.35 | D27: 0.30798375 | E27: 0.26596751 | F27: 0.22395126 | G27: 0.18193501 | H27: 0.13991877 | I27: 0.097902522 | J27: 0.097902522 | K27: 0.097902522
A28: D&A % of revenue | B28: 0.043130617 | C28: 0.043130617 | D28: 0.043130617 | E28: 0.043130617 | F28: 0.043130617 | G28: 0.043130617 | H28: 0.043130617 | I28: 0.043130617 | J28: 0.043130617 | K28: 0.043130617
A29: Capex % of revenue | B29: 0.029544721 | C29: 0.031533494 | D29: 0.033522267 | E29: 0.03551104 | F29: 0.037499813 | G29: 0.039488587 | H29: 0.04147736 | I29: 0.043466133 | J29: 0.045454906 | K29: 0.047443679
A30: ΔNWC % of Δrevenue | B30: 0.14904679

Sheet WACC
A1: Cost of capital (CAPM)
A2: All formulas reference the Assumptions sheet.
A4: Cost of equity (Ke = Rf + β·ERP + CRP + size) | B4: =Assumptions!$B$13+Assumptions!$B$17*Assumptions!$B$14+Assumptions!$B$15+Assumptions!$B$16
A5: After-tax cost of debt (Kd·(1−t)) | B5: =Assumptions!$B$18*(1-Assumptions!$B$19)
A6: Market value of equity (mm) | B6: =Assumptions!$B$5*Assumptions!$B$6
A7: Debt (book, mm) | B7: =Assumptions!$B$7
A8: Weight of equity | B8: =WACC!$B$6/(WACC!$B$6+WACC!$B$7)
A9: Weight of debt | B9: =1-WACC!$B$8
A10: WACC | B10: =WACC!$B$8*WACC!$B$4+WACC!$B$9*WACC!$B$5

Sheet Model
A1: Operating model (USDmm)
A2: Shaded columns are reported actuals (blue hardcodes, sourced); unshaded are forecast formulas driven by the Assumptions sheet.
A4: Line item | B4: FY2023A | C4: FY2024A | D4: FY2025A | E4: FY2026E | F4: FY2027E | G4: FY2028E | H4: FY2029E | I4: FY2030E | J4: FY2031E | K4: FY2032E | L4: FY2033E | M4: FY2034E | N4: FY2035E
A5: Revenue | B5: 6086 | C5: 6663 | D5: 7355 | E5: =D5*(1+Assumptions!B$26) | F5: =E5*(1+Assumptions!C$26) | G5: =F5*(1+Assumptions!D$26) | H5: =G5*(1+Assumptions!E$26) | I5: =H5*(1+Assumptions!F$26) | J5: =I5*(1+Assumptions!G$26) | K5: =J5*(1+Assumptions!H$26) | L5: =K5*(1+Assumptions!I$26) | ... N5: =M5*(1+Assumptions!K$26)
A6: growth % | C6: =C5/B5-1 | D6: =D5/C5-1 | E6: =E5/D5-1 | F6: =F5/E5-1 | G6: =G5/F5-1 | H6: =H5/G5-1 | I6: =I5/H5-1 | J6: =J5/I5-1 | ... N6: =N5/M5-1
A7: EBIT | B7: -1295 | C7: -444 | D7: 507 | E7: =E5*Assumptions!B$27 | F7: =F5*Assumptions!C$27 | G7: =G5*Assumptions!D$27 | H7: =H5*Assumptions!E$27 | I7: =I5*Assumptions!F$27 | J7: =J5*Assumptions!G$27 | K7: =K5*Assumptions!H$27 | L7: =L5*Assumptions!I$27 | ... N7: =N5*Assumptions!K$27
A8: EBIT margin % | B8: =B7/B5 | C8: =C7/C5 | D8: =D7/D5 | E8: =E7/E5 | F8: =F7/F5 | G8: =G7/G5 | H8: =H7/H5 | I8: =I7/I5 | ... N8: =N7/N5
A9: D&A | B9: 448 | C9: 224 | D9: 163 | E9: =E5*Assumptions!B$28 | F9: =F5*Assumptions!C$28 | G9: =G5*Assumptions!D$28 | H9: =H5*Assumptions!E$28 | I9: =I5*Assumptions!F$28 | J9: =J5*Assumptions!G$28 | K9: =K5*Assumptions!H$28 | L9: =L5*Assumptions!I$28 | ... N9: =N5*Assumptions!K$28
A10: EBITDA | B10: =B7+B9 | C10: =C7+C9 | D10: =D7+D9 | E10: =E7+E9 | F10: =F7+F9 | G10: =G7+G9 | H10: =H7+H9 | I10: =I7+I9 | ... N10: =N7+N9
A11: NOPAT (EBIT×(1−t)) | B11: =B7*(1-Assumptions!$B$19) | C11: =C7*(1-Assumptions!$B$19) | D11: =D7*(1-Assumptions!$B$19) | E11: =E7*(1-Assumptions!$B$19) | F11: =F7*(1-Assumptions!$B$19) | G11: =G7*(1-Assumptions!$B$19) | H11: =H7*(1-Assumptions!$B$19) | I11: =I7*(1-Assumptions!$B$19) | ... N11: =N7*(1-Assumptions!$B$19)
A12: Capex | B12: 219 | C12: 166 | D12: 204 | E12: =E5*Assumptions!B$29 | F12: =F5*Assumptions!C$29 | G12: =G5*Assumptions!D$29 | H12: =H5*Assumptions!E$29 | I12: =I5*Assumptions!F$29 | J12: =J5*Assumptions!G$29 | K12: =K5*Assumptions!H$29 | L12: =L5*Assumptions!I$29 | ... N12: =N5*Assumptions!K$29
A13: Δ Net working capital | B13: -197 | C13: 86 | D13: 380 | E13: =(E5-D5)*Assumptions!$B$30 | F13: =(F5-E5)*Assumptions!$B$30 | G13: =(G5-F5)*Assumptions!$B$30 | H13: =(H5-G5)*Assumptions!$B$30 | I13: =(I5-H5)*Assumptions!$B$30 | J13: =(J5-I5)*Assumptions!$B$30 | K13: =(K5-J5)*Assumptions!$B$30 | L13: =(L5-K5)*Assumptions!$B$30 | ... N13: =(N5-M5)*Assumptions!$B$30
A14: FCFF | B14: =B11+B9-B12-B13 | C14: =C11+C9-C12-C13 | D14: =D11+D9-D12-D13 | E14: =E11+E9-E12-E13 | F14: =F11+F9-F12-F13 | G14: =G11+G9-G12-G13 | H14: =H11+H9-H12-H13 | I14: =I11+I9-I12-I13 | ... N14: =N11+N9-N12-N13

Sheet DCF
A1: Discounted cash flow (USDmm)
A2: Mid-year convention. Terminal value is reinvestment-consistent: TV = NOPATn·(1+g)·(1−g/ROIC)/(WACC−g).
A4: Year | B4: FY2026E | C4: FY2027E | D4: FY2028E | E4: FY2029E | F4: FY2030E | G4: FY2031E | H4: FY2032E | I4: FY2033E | J4: FY2034E | K4: FY2035E
A5: FCFF (from Model) | B5: =Model!E14 | C5: =Model!F14 | D5: =Model!G14 | E5: =Model!H14 | F5: =Model!I14 | G5: =Model!J14 | H5: =Model!K14 | I5: =Model!L14 | ... K5: =Model!N14
A6: Period (mid-year, t−0.5) | B6: 0.5 | C6: 1.5 | D6: 2.5 | E6: 3.5 | F6: 4.5 | G6: 5.5 | H6: 6.5 | I6: 7.5 | J6: 8.5 | K6: 9.5
A7: Discount factor | B7: =1/(1+WACC!$B$10)^B6 | C7: =1/(1+WACC!$B$10)^C6 | D7: =1/(1+WACC!$B$10)^D6 | E7: =1/(1+WACC!$B$10)^E6 | F7: =1/(1+WACC!$B$10)^F6 | G7: =1/(1+WACC!$B$10)^G6 | H7: =1/(1+WACC!$B$10)^H6 | I7: =1/(1+WACC!$B$10)^I6 | ... K7: =1/(1+WACC!$B$10)^K6
A8: PV of FCFF | B8: =B5*B7 | C8: =C5*C7 | D8: =D5*D7 | E8: =E5*E7 | F8: =F5*F7 | G8: =G5*G7 | H8: =H5*H7 | I8: =I5*I7 | ... K8: =K5*K7
A10: PV of explicit FCFF | B10: =SUM(B8:K8)
A11: Terminal NOPAT (FYn) | B11: =Model!N11
A12: Invested capital (mm) | B12: 9777
A13: Terminal invested capital (scaled w/ revenue) | B13: =$B$12*Model!N5/Model!D5
A14: Terminal ROIC | B14: =MAX($B$11/$B$13,WACC!$B$10)
A15: Terminal reinvestment rate (g/ROIC) | B15: =Assumptions!$B$22/$B$14
A16: Terminal value (Gordon) | B16: =$B$11*(1+Assumptions!$B$22)*(1-$B$15)/(WACC!$B$10-Assumptions!$B$22)
A17: PV of terminal value | B17: =$B$16/(1+WACC!$B$10)^(10-0.5)
A18: TV as % of EV | B18: =$B$17/($B$10+$B$17)
A20: Enterprise value | B20: =$B$10+$B$17
A21: (−) Net debt | B21: =-Assumptions!$B$10
A22: (−) Minority interest | B22: =-Assumptions!$B$9
A23: Equity value | B23: =$B$20-Assumptions!$B$10-Assumptions!$B$9
A24: Value per share | B24: =$B$23/Assumptions!$B$6
A25: Upside vs price | B25: =$B$24/Assumptions!$B$5-1

Sheet Sensitivity
A1: Value per share — WACC × terminal growth (USD/share)
A2: Every cell is a live formula; it re-runs the full DCF at that WACC/g pair.
A4: WACC \ g | B4: 0.015 | C4: 0.02 | D4: 0.025 | E4: 0.03 | F4: 0.035
A5: 0.078462187 | B5: =(SUMPRODUCT(DCF!$B$5:$K$5,1/(1+$A$5)^DCF!$B$6:$K$6)+DCF!$B$11*(1+B$4)*(1-B$4/DCF!$B$14)/($A$5-B$4)/(1+$A$5)^(10-0.5)-Assumptions!$B$10-Assumptions!$B$9)/Assumptions!$B$6 | C5: =(SUMPRODUCT(DCF!$B$5:$K$5,1/(1+$A$5)^DCF!$B$6:$K$6)+DCF!$B$11*(1+C$4)*(1-C$4/DCF!$B$14)/($A$5-C$4)/(1+$A$5)^(10-0.5)-Assumptions!$B$10-Assumptions!$B$9)/Assumptions!$B$6 | D5: =(SUMPRODUCT(DCF!$B$5:$K$5,1/(1+$A$5)^DCF!$B$6:$K$6)+DCF!$B$11*(1+D$4)*(1-D$4/DCF!$B$14)/($A$5-D$4)/(1+$A$5)^(10-0.5)-Assumptions!$B$10-Assumptions!$B$9)/Assumptions!$B$6 | E5: =(SUMPRODUCT(DCF!$B$5:$K$5,1/(1+$A$5)^DCF!$B$6:$K$6)+DCF!$B$11*(1+E$4)*(1-E$4/DCF!$B$14)/($A$5-E$4)/(1+$A$5)^(10-0.5)-Assumptions!$B$10-Assumptions!$B$9)/Assumptions!$B$6 | F5: =(SUMPRODUCT(DCF!$B$5:$K$5,1/(1+$A$5)^DCF!$B$6:$K$6)+DCF!$B$11*(1+F$4)*(1-F$4/DCF!$B$14)/($A$5-F$4)/(1+$A$5)^(10-0.5)-Assumptions!$B$10-Assumptions!$B$9)/Assumptions!$B$6
A6: 0.085962187 | B6: =(SUMPRODUCT(DCF!$B$5:$K$5,1/(1+$A$6)^DCF!$B$6:$K$6)+DCF!$B$11*(1+B$4)*(1-B$4/DCF!$B$14)/($A$6-B$4)/(1+$A$6)^(10-0.5)-Assumptions!$B$10-Assumptions!$B$9)/Assumptions!$B$6 | C6: =(SUMPRODUCT(DCF!$B$5:$K$5,1/(1+$A$6)^DCF!$B$6:$K$6)+DCF!$B$11*(1+C$4)*(1-C$4/DCF!$B$14)/($A$6-C$4)/(1+$A$6)^(10-0.5)-Assumptions!$B$10-Assumptions!$B$9)/Assumptions!$B$6 | D6: =(SUMPRODUCT(DCF!$B$5:$K$5,1/(1+$A$6)^DCF!$B$6:$K$6)+DCF!$B$11*(1+D$4)*(1-D$4/DCF!$B$14)/($A$6-D$4)/(1+$A$6)^(10-0.5)-Assumptions!$B$10-Assumptions!$B$9)/Assumptions!$B$6 | E6: =(SUMPRODUCT(DCF!$B$5:$K$5,1/(1+$A$6)^DCF!$B$6:$K$6)+DCF!$B$11*(1+E$4)*(1-E$4/DCF!$B$14)/($A$6-E$4)/(1+$A$6)^(10-0.5)-Assumptions!$B$10-Assumptions!$B$9)/Assumptions!$B$6 | F6: =(SUMPRODUCT(DCF!$B$5:$K$5,1/(1+$A$6)^DCF!$B$6:$K$6)+DCF!$B$11*(1+F$4)*(1-F$4/DCF!$B$14)/($A$6-F$4)/(1+$A$6)^(10-0.5)-Assumptions!$B$10-Assumptions!$B$9)/Assumptions!$B$6
A7: 0.093462187 | B7: =(SUMPRODUCT(DCF!$B$5:$K$5,1/(1+$A$7)^DCF!$B$6:$K$6)+DCF!$B$11*(1+B$4)*(1-B$4/DCF!$B$14)/($A$7-B$4)/(1+$A$7)^(10-0.5)-Assumptions!$B$10-Assumptions!$B$9)/Assumptions!$B$6 | C7: =(SUMPRODUCT(DCF!$B$5:$K$5,1/(1+$A$7)^DCF!$B$6:$K$6)+DCF!$B$11*(1+C$4)*(1-C$4/DCF!$B$14)/($A$7-C$4)/(1+$A$7)^(10-0.5)-Assumptions!$B$10-Assumptions!$B$9)/Assumptions!$B$6 | D7: =(SUMPRODUCT(DCF!$B$5:$K$5,1/(1+$A$7)^DCF!$B$6:$K$6)+DCF!$B$11*(1+D$4)*(1-D$4/DCF!$B$14)/($A$7-D$4)/(1+$A$7)^(10-0.5)-Assumptions!$B$10-Assumptions!$B$9)/Assumptions!$B$6 | E7: =(SUMPRODUCT(DCF!$B$5:$K$5,1/(1+$A$7)^DCF!$B$6:$K$6)+DCF!$B$11*(1+E$4)*(1-E$4/DCF!$B$14)/($A$7-E$4)/(1+$A$7)^(10-0.5)-Assumptions!$B$10-Assumptions!$B$9)/Assumptions!$B$6 | F7: =(SUMPRODUCT(DCF!$B$5:$K$5,1/(1+$A$7)^DCF!$B$6:$K$6)+DCF!$B$11*(1+F$4)*(1-F$4/DCF!$B$14)/($A$7-F$4)/(1+$A$7)^(10-0.5)-Assumptions!$B$10-Assumptions!$B$9)/Assumptions!$B$6
A8: 0.10096219 | B8: =(SUMPRODUCT(DCF!$B$5:$K$5,1/(1+$A$8)^DCF!$B$6:$K$6)+DCF!$B$11*(1+B$4)*(1-B$4/DCF!$B$14)/($A$8-B$4)/(1+$A$8)^(10-0.5)-Assumptions!$B$10-Assumptions!$B$9)/Assumptions!$B$6 | C8: =(SUMPRODUCT(DCF!$B$5:$K$5,1/(1+$A$8)^DCF!$B$6:$K$6)+DCF!$B$11*(1+C$4)*(1-C$4/DCF!$B$14)/($A$8-C$4)/(1+$A$8)^(10-0.5)-Assumptions!$B$10-Assumptions!$B$9)/Assumptions!$B$6 | D8: =(SUMPRODUCT(DCF!$B$5:$K$5,1/(1+$A$8)^DCF!$B$6:$K$6)+DCF!$B$11*(1+D$4)*(1-D$4/DCF!$B$14)/($A$8-D$4)/(1+$A$8)^(10-0.5)-Assumptions!$B$10-Assumptions!$B$9)/Assumptions!$B$6 | E8: =(SUMPRODUCT(DCF!$B$5:$K$5,1/(1+$A$8)^DCF!$B$6:$K$6)+DCF!$B$11*(1+E$4)*(1-E$4/DCF!$B$14)/($A$8-E$4)/(1+$A$8)^(10-0.5)-Assumptions!$B$10-Assumptions!$B$9)/Assumptions!$B$6 | F8: =(SUMPRODUCT(DCF!$B$5:$K$5,1/(1+$A$8)^DCF!$B$6:$K$6)+DCF!$B$11*(1+F$4)*(1-F$4/DCF!$B$14)/($A$8-F$4)/(1+$A$8)^(10-0.5)-Assumptions!$B$10-Assumptions!$B$9)/Assumptions!$B$6
A9: 0.10846219 | B9: =(SUMPRODUCT(DCF!$B$5:$K$5,1/(1+$A$9)^DCF!$B$6:$K$6)+DCF!$B$11*(1+B$4)*(1-B$4/DCF!$B$14)/($A$9-B$4)/(1+$A$9)^(10-0.5)-Assumptions!$B$10-Assumptions!$B$9)/Assumptions!$B$6 | C9: =(SUMPRODUCT(DCF!$B$5:$K$5,1/(1+$A$9)^DCF!$B$6:$K$6)+DCF!$B$11*(1+C$4)*(1-C$4/DCF!$B$14)/($A$9-C$4)/(1+$A$9)^(10-0.5)-Assumptions!$B$10-Assumptions!$B$9)/Assumptions!$B$6 | D9: =(SUMPRODUCT(DCF!$B$5:$K$5,1/(1+$A$9)^DCF!$B$6:$K$6)+DCF!$B$11*(1+D$4)*(1-D$4/DCF!$B$14)/($A$9-D$4)/(1+$A$9)^(10-0.5)-Assumptions!$B$10-Assumptions!$B$9)/Assumptions!$B$6 | E9: =(SUMPRODUCT(DCF!$B$5:$K$5,1/(1+$A$9)^DCF!$B$6:$K$6)+DCF!$B$11*(1+E$4)*(1-E$4/DCF!$B$14)/($A$9-E$4)/(1+$A$9)^(10-0.5)-Assumptions!$B$10-Assumptions!$B$9)/Assumptions!$B$6 | F9: =(SUMPRODUCT(DCF!$B$5:$K$5,1/(1+$A$9)^DCF!$B$6:$K$6)+DCF!$B$11*(1+F$4)*(1-F$4/DCF!$B$14)/($A$9-F$4)/(1+$A$9)^(10-0.5)-Assumptions!$B$10-Assumptions!$B$9)/Assumptions!$B$6

Sheet IS (reported)
A1: SNDK — IS (reported)
A2: As reported by Yahoo snapshot as of 2026-07-09 (USDmm). Hardcoded actuals.
A4: Line item | B4: FY2023 | C4: FY2024 | D4: FY2025
A5: Tax Effect Of Unusual Items | B5: -155.4 | C5: -5.04 | D5: -395.64
A6: Tax Rate For Calcs | B6: 2.1e-13 | C6: 2.1e-13 | D6: 2.1e-13
A7: Normalized EBITDA | B7: -783 | C7: -215 | D7: 631
A8: Total Unusual Items | B8: -740 | C8: -24 | D8: -1884
A9: Total Unusual Items Excluding Goodwill | B9: -740 | C9: -24 | D9: -1884
A10: Net Income From Continuing Operation Net Minority Interest | B10: -2143 | C10: -672 | D10: -1641
A11: Reconciled Depreciation | B11: 448 | C11: 224 | D11: 163
A12: Reconciled Cost Of Revenue | B12: 5656 | C12: 5591 | D12: 5143
A13: EBITDA | B13: -1523 | C13: -239 | D13: -1253
A14: EBIT | B14: -1971 | C14: -463 | D14: -1416
A15: Net Interest Income | B15: -10 | C15: -28 | D15: -41
A16: Interest Expense | B16: 31 | C16: 40 | D16: 63
... A49: Operating Revenue | B49: 6086 | C49: 6663 | D49: 7355

Sheet BS (reported)
A1: SNDK — BS (reported)
A2: As reported by Yahoo snapshot as of 2026-07-09 (USDmm). Hardcoded actuals.
A4: Line item | B4: FY2024 | C4: FY2025
A5: Ordinary Shares Number | C5: 146
A6: Share Issued | C6: 146
A7: Net Debt | B7: 486 | C7: 368
A8: Total Debt | B8: 985 | C8: 2042
A9: Tangible Book Value | B9: 3875 | C9: 4217
A10: Invested Capital | B10: 11896 | C10: 11065
A11: Working Capital | B11: 1425 | C11: 3659
A12: Net Tangible Assets | B12: 3875 | C12: 4217
A13: Capital Lease Obligations | B13: 171 | C13: 193
A14: Common Stock Equity | B14: 11082 | C14: 9216
A15: Total Capitalization | B15: 11082 | C15: 11045
A16: Total Equity Gross Minority Interest | B16: 11082 | C16: 9216
A17: Stockholders Equity | B17: 11082 | C17: 9216
A18: Gains Losses Not Affecting Retained Earnings | B18: -452 | C18: -249
... A31: Long Term Capital Lease Obligation | B31: 171 | C31: 193
A32: Long Term Debt | C32: 1829
A33: Current Liabilities | B33: 2123 | C33: 1427
A34: Current Debt And Capital Lease Obligation | B34: 814 | C34: 20
A35: Current Debt | B35: 814 | C35: 20
A36: Other Current Borrowings | C36: 20
A37: Current Notes Payable | B37: 814 | C37: 0
A38: Payables And Accrued Expenses | B38: 1309 | C38: 1407
A39: Current Accrued Expenses | B39: 619 | C39: 598
A40: Payables | B40: 690 | C40: 809
A41: Dueto Related Parties Current | B41: 313 | C41: 400
A42: Total Tax Payable | B42: 20 | C42: 43
A43: Income Tax Payable | B43: 20 | C43: 43
A44: Accounts Payable | B44: 357 | C44: 366
A45: Total Assets | B45: 13506 | C45: 12985
A46: Total Non Current Assets | B46: 9958 | C46: 7899
A47: Other Non Current Assets | B47: 852 | C47: 1489
A48: Non Current Deferred Assets | B48: 96 | C48: 58
... A73: Cash And Cash Equivalents | B73: 328 | C73: 1481

Sheet CF (reported)
A1: SNDK — CF (reported)
A2: As reported by Yahoo snapshot as of 2026-07-09 (USDmm). Hardcoded actuals.
A4: Line item | B4: FY2023 | C4: FY2024 | D4: FY2025
A5: Free Cash Flow | B5: -932 | C5: -475 | D5: -120
A6: Repayment Of Debt | B6: -86 | C6: -272 | D6: -176
A7: Issuance Of Debt | B7: 270 | C7: 14 | D7: 2621
A8: Capital Expenditure | B8: -219 | C8: -166 | D8: -204
A9: Interest Paid Supplemental Data | B9: 7 | C9: 12 | D9: 139
A10: Income Tax Paid Supplemental Data | B10: 0 | C10: 0 | D10: 50
A11: End Cash Position | B11: 292 | C11: 328 | D11: 1481
A12: Beginning Cash Position | B12: 335 | C12: 292 | D12: 328
A13: Effect Of Exchange Rate Changes | B13: -1 | C13: -1 | D13: -5
A14: Changes In Cash | B14: -42 | C14: 37 | D14: 1158
A15: Financing Cash Flow | B15: 860 | C15: 136 | D15: 518
A16: Cash Flow From Continuing Financing Activities | B16: 860 | C16: 136 | D16: 518
... A52: Depreciation And Amortization | B52: 448 | C52: 224 | D52: 163
A53: Amortization Cash Flow | B53: 133
A54: Amortization Of Intangibles | B54: 133
A55: Depreciation | B55: 315 | C55: 224 | D55: 163
A56: Operating Gains Losses | B56: -85 | C56: 1 | D56: 14
A57: Earnings Losses From Equity Investments | B57: -45 | C57: 49 | D57: 74
A58: Gain Loss On Investment Securities | B58: -3 | C58: -1
A59: Net Foreign Currency Exchange Gain Loss | B59: -37 | C59: 13 | D59: -25
A60: Gain Loss On Sale Of Business | B60: 0 | C60: 0 | D60: -34
A61: Net Income From Continuing Operations | B61: -2143 | C61: -672 | D61: -1641
