Workbook

Sheet Cover
A1: Meridian Industrials (illustrative) (DEMO)
A2: Industrials · Standard (forward multiples + DCF) · generated 2026-10-13 · data: DEMO (synthetic)
A4: Current price | B4: =Assumptions!$B$5
A5: DCF value per share (one lens) | B5: =DCF!$B$24
A6: Upside / downside | B6: =DCF!$B$24/Assumptions!$B$5-1
A7: 12-month price target (report) | B7: 294.20094
A8: WACC | B8: =WACC!$B$10
A10: How to use
A11: Blue cells are inputs — edit growth, margins, beta, ERP or terminal g
A12: in the Assumptions sheet and everything recalculates live.
A13: Black cells are formulas; green cells link across sheets.
A14: The Sensitivity grid re-runs the full DCF per WACC/g pair.
A15: Not investment advice. Verify source data before relying on outputs.

Sheet Target Price
A1: DEMO — 12-month price target (lens triangulation)
A2: Blue = inputs (weights, Ke, dividends, Street weight); black = live formulas. Change a weight and the blended fair value and target recalculate. Guardrail exclusions are already reflected in the effective weights.
A4: Lens | B4: Type | C4: Value / share | D4: Low | E4: High | F4: Weight | G4: Status
A5: Discounted cash flow (FCFF) | B5: intrinsic | C5: 230.26794 | D5: 195.79324 | E5: 270.37396 | F5: 0.38888889 | G5: ok
A6: Forward P/E | B6: relative | C6: 299.27409 | D6: 245.40476 | E6: 353.14343 | F6: 0.33333333 | G6: ok
A7: Forward EV/EBITDA | B7: relative | C7: 308.76722 | D7: 253.2128 | E7: 364.32163 | F7: 0.27777778 | G7: ok
A9: Weights sum | B9: =SUM(F5:F7)
A10: Blended fair value (today) | B10: =SUMPRODUCT(C5:C7,F5:F7)/SUM(F5:F7)
A11: Cost of equity (Ke) | B11: 0.092588639
A12: Dividends per share (12m) | B12: 2.4
A13: Model 12-month target = FV×(1+Ke)−DPS | B13: =$B$10*(1+$B$11)-$B$12
A14: Street mean target | B14: 285
A15: Street weight in target | B15: 0.3
A16: Published 12-month target | B16: =(1-$B$15)*$B$13+$B$15*$B$14
A17: Current price | B17: 262
A18: Engine target (incl. plausibility band) | B18: 294.20094
A20: Guardrails
A21: Target anchored 30% to the Street consensus ($285.00, 24 analysts); model-only target $298.14.

Sheet Financial Model
A1: DEMO — projected P&L & levered FCF (DCF base case)
A2: Blue = consensus-sourced figures; black = live formulas. Revenue and EBIT margin are the DCF base-case drivers; levered FCF = unlevered FCF less after-tax interest.
A4: Line item | B4: FY2026E | C4: FY2027E | D4: FY2028E | E4: FY2029E | F4: FY2030E | G4: FY2031E | H4: FY2032E | I4: FY2033E | J4: FY2034E | K4: FY2035E
A5: Revenue (mn) | B5: 91976.027 | C5: 97242.501 | D5: 101922.36 | E5: 106160.11 | F5: 110075.76 | G5: 113765.45 | H5: 117304.4 | I5: 120750.6 | J5: 124148.36 | K5: 127252.07
A6: Revenue growth | B6: — | C6: =C5/B5-1 | D6: =D5/C5-1 | E6: =E5/D5-1 | F6: =F5/E5-1 | G6: =G5/F5-1 | H6: =H5/G5-1 | I6: =I5/H5-1 | J6: =J5/I5-1 | K6: =K5/J5-1
A7: EBIT margin | B7: 0.28690811 | C7: 0.28629062 | D7: 0.28567313 | E7: 0.28505564 | F7: 0.28443814 | G7: 0.28382065 | H7: 0.28320316 | I7: 0.28258567 | J7: 0.28258567 | K7: 0.28258567
A8: EBIT (mn) | B8: =B5*B7 | C8: =C5*C7 | D8: =D5*D7 | E8: =E5*E7 | F8: =F5*F7 | G8: =G5*G7 | H8: =H5*H7 | I8: =I5*I7 | ... K8: =K5*K7
A9: Net income (mn) | B9: 20929.321 | C9: 22104.589 | D9: 23138.849 | E9: 24066.345 | F9: 24915.393 | G9: 25708.577 | H9: 26463.492 | I9: 27193.636 | J9: 27971.363 | K9: 28681.785
A10: EPS | B10: =B9*1000000/1520000000.0 | C10: =C9*1000000/1520000000.0 | D10: =D9*1000000/1520000000.0 | E10: =E9*1000000/1520000000.0 | F10: =F9*1000000/1520000000.0 | G10: =G9*1000000/1520000000.0 | H10: =H9*1000000/1520000000.0 | I10: =I9*1000000/1520000000.0 | ... K10: =K9*1000000/1520000000.0
A12: Levered FCF (mn) | B12: 20305.78 | C12: 21526.395 | D12: 22567.06 | E12: 23467.172 | F12: 24260.424 | G12: 24974.219 | H12: 25630.128 | I12: 26244.768 | J12: 26892.849 | K12: 27508.674
A13: FCF margin | B13: =B12/B5 | C13: =C12/C5 | D13: =D12/D5 | E13: =E12/E5 | F13: =F12/F5 | G13: =G12/G5 | H13: =H12/H5 | I13: =I12/I5 | ... K13: =K12/K5
A15: → Unlevered FCF (before interest) is what the 'DCF' sheet discounts.

Sheet Assumptions
A1: DEMO — Assumptions & Drivers
A2: Blue cells are inputs — change them and the whole model recalculates. Source: DEMO (synthetic), retrieved 2026-10-13.
A4: Market data
A5: Share price (USD) | B5: 262
A6: Diluted shares (mn) | B6: 1520
A7: Total debt (USDmm) | B7: 12000
A8: Cash & ST investments (USDmm) | B8: 12500
A9: Minority interest (USDmm) | B9: 300
A10: Net debt (USDmm) | B10: =Assumptions!$B$7-Assumptions!$B$8
A12: Cost of capital inputs
A13: Risk-free rate (Rf) | B13: 0.043
A14: Equity risk premium (ERP) | B14: 0.046
A15: Country risk premium | B15: 0
A16: Size premium | B16: 0
A17: Beta (levered) | B17: 1.08
A18: Pre-tax cost of debt | B18: 0.049
A19: Tax rate | B19: 0.19
A21: Terminal assumptions
A22: Terminal growth (g) | B22: 0.025
A24: Per-year forecast drivers
A25: Driver | B25: FY2026E | C25: FY2027E | D25: FY2028E | E25: FY2029E | F25: FY2030E | G25: FY2031E | H25: FY2032E | I25: FY2033E | J25: FY2034E | K25: FY2035E
A26: Revenue growth | B26: 0.07 | C26: 0.057259202 | D26: 0.048125692 | E26: 0.041578142 | F26: 0.036884392 | G26: 0.033519578 | H26: 0.03110744 | I26: 0.029378247 | J26: 0.028138639 | K26: 0.025
A27: EBIT margin | B27: 0.28690811 | C27: 0.28629062 | D27: 0.28567313 | E27: 0.28505564 | F27: 0.28443814 | G27: 0.28382065 | H27: 0.28320316 | I27: 0.28258567 | J27: 0.28258567 | K27: 0.28258567
A28: D&A % of revenue | B28: 0.052 | C28: 0.052 | D28: 0.052 | E28: 0.052 | F28: 0.052 | G28: 0.052 | H28: 0.052 | I28: 0.052 | J28: 0.052 | K28: 0.052
A29: Capex % of revenue | B29: 0.048 | C29: 0.049022222 | D29: 0.050044444 | E29: 0.051066667 | F29: 0.052088889 | G29: 0.053111111 | H29: 0.054133333 | I29: 0.055155556 | J29: 0.056177778 | K29: 0.0572
A30: ΔNWC % of Δrevenue | B30: 0.16477056

Sheet WACC
A1: Cost of capital (CAPM)
A2: All formulas reference the Assumptions sheet.
A4: Cost of equity (Ke = Rf + β·ERP + CRP + size) | B4: =Assumptions!$B$13+Assumptions!$B$17*Assumptions!$B$14+Assumptions!$B$15+Assumptions!$B$16
A5: After-tax cost of debt (Kd·(1−t)) | B5: =Assumptions!$B$18*(1-Assumptions!$B$19)
A6: Market value of equity (mm) | B6: =Assumptions!$B$5*Assumptions!$B$6
A7: Debt (book, mm) | B7: =Assumptions!$B$7
A8: Weight of equity | B8: =WACC!$B$6/(WACC!$B$6+WACC!$B$7)
A9: Weight of debt | B9: =1-WACC!$B$8
A10: WACC | B10: =WACC!$B$8*WACC!$B$4+WACC!$B$9*WACC!$B$5

Sheet Model
A1: Operating model (USDmm)
A2: Shaded columns are reported actuals (blue hardcodes, sourced); unshaded are forecast formulas driven by the Assumptions sheet.
A4: Line item | B4: FY2022A | C4: FY2023A | D4: FY2024A | E4: FY2025A | F4: FY2026E | G4: FY2027E | H4: FY2028E | I4: FY2029E | J4: FY2030E | K4: FY2031E | L4: FY2032E | M4: FY2033E | N4: FY2034E | O4: FY2035E
A5: Revenue | B5: 70174.2 | C5: 75086.394 | D5: 81093.306 | E5: 85958.904 | F5: =E5*(1+Assumptions!B$26) | G5: =F5*(1+Assumptions!C$26) | H5: =G5*(1+Assumptions!D$26) | I5: =H5*(1+Assumptions!E$26) | J5: =I5*(1+Assumptions!F$26) | K5: =J5*(1+Assumptions!G$26) | L5: =K5*(1+Assumptions!H$26) | M5: =L5*(1+Assumptions!I$26) | ... O5: =N5*(1+Assumptions!K$26)
A6: growth % | C6: =C5/B5-1 | D6: =D5/C5-1 | E6: =E5/D5-1 | F6: =F5/E5-1 | G6: =G5/F5-1 | H6: =H5/G5-1 | I6: =I5/H5-1 | J6: =J5/I5-1 | ... O6: =O5/N5-1
A7: EBIT | B7: 18947.034 | C7: 20648.758 | D7: 22706.126 | E7: 24498.288 | F7: =F5*Assumptions!B$27 | G7: =G5*Assumptions!C$27 | H7: =H5*Assumptions!D$27 | I7: =I5*Assumptions!E$27 | J7: =J5*Assumptions!F$27 | K7: =K5*Assumptions!G$27 | L7: =L5*Assumptions!H$27 | M7: =M5*Assumptions!I$27 | ... O7: =O5*Assumptions!K$27
A8: EBIT margin % | B8: =B7/B5 | C8: =C7/C5 | D8: =D7/D5 | E8: =E7/E5 | F8: =F7/F5 | G8: =G7/G5 | H8: =H7/H5 | I8: =I7/I5 | ... O8: =O7/O5
A9: D&A | B9: 3649.0584 | C9: 3904.4925 | D9: 4216.8519 | E9: 4469.863 | F9: =F5*Assumptions!B$28 | G9: =G5*Assumptions!C$28 | H9: =H5*Assumptions!D$28 | I9: =I5*Assumptions!E$28 | J9: =J5*Assumptions!F$28 | K9: =K5*Assumptions!G$28 | L9: =L5*Assumptions!H$28 | M9: =M5*Assumptions!I$28 | ... O9: =O5*Assumptions!K$28
A10: EBITDA | B10: =B7+B9 | C10: =C7+C9 | D10: =D7+D9 | E10: =E7+E9 | F10: =F7+F9 | G10: =G7+G9 | H10: =H7+H9 | I10: =I7+I9 | ... O10: =O7+O9
A11: NOPAT (EBIT×(1−t)) | B11: =B7*(1-Assumptions!$B$19) | C11: =C7*(1-Assumptions!$B$19) | D11: =D7*(1-Assumptions!$B$19) | E11: =E7*(1-Assumptions!$B$19) | F11: =F7*(1-Assumptions!$B$19) | G11: =G7*(1-Assumptions!$B$19) | H11: =H7*(1-Assumptions!$B$19) | I11: =I7*(1-Assumptions!$B$19) | ... O11: =O7*(1-Assumptions!$B$19)
A12: Capex | B12: 3368.3616 | C12: 3604.1469 | D12: 3892.4787 | E12: 4126.0274 | F12: =F5*Assumptions!B$29 | G12: =G5*Assumptions!C$29 | H12: =H5*Assumptions!D$29 | I12: =I5*Assumptions!E$29 | J12: =J5*Assumptions!F$29 | K12: =K5*Assumptions!G$29 | L12: =L5*Assumptions!H$29 | M12: =M5*Assumptions!I$29 | ... O12: =O5*Assumptions!K$29
A13: Δ Net working capital | B13: 842.0904 | C13: 901.03673 | D13: 973.11967 | E13: 1031.5068 | F13: =(F5-E5)*Assumptions!$B$30 | G13: =(G5-F5)*Assumptions!$B$30 | H13: =(H5-G5)*Assumptions!$B$30 | I13: =(I5-H5)*Assumptions!$B$30 | J13: =(J5-I5)*Assumptions!$B$30 | K13: =(K5-J5)*Assumptions!$B$30 | L13: =(L5-K5)*Assumptions!$B$30 | M13: =(M5-L5)*Assumptions!$B$30 | ... O13: =(O5-N5)*Assumptions!$B$30
A14: FCFF | B14: =B11+B9-B12-B13 | C14: =C11+C9-C12-C13 | D14: =D11+D9-D12-D13 | E14: =E11+E9-E12-E13 | F14: =F11+F9-F12-F13 | G14: =G11+G9-G12-G13 | H14: =H11+H9-H12-H13 | I14: =I11+I9-I12-I13 | ... O14: =O11+O9-O12-O13

Sheet DCF
A1: Discounted cash flow (USDmm)
A2: Mid-year convention. Terminal value is reinvestment-consistent: TV = NOPATn·(1+g)·(1−g/ROIC)/(WACC−g).
A4: Year | B4: FY2026E | C4: FY2027E | D4: FY2028E | E4: FY2029E | F4: FY2030E | G4: FY2031E | H4: FY2032E | I4: FY2033E | J4: FY2034E | K4: FY2035E
A5: FCFF (from Model) | B5: =Model!F14 | C5: =Model!G14 | D5: =Model!H14 | E5: =Model!I14 | F5: =Model!J14 | G5: =Model!K14 | H5: =Model!L14 | I5: =Model!M14 | ... K5: =Model!O14
A6: Period (mid-year, t−0.5) | B6: 0.5 | C6: 1.5 | D6: 2.5 | E6: 3.5 | F6: 4.5 | G6: 5.5 | H6: 6.5 | I6: 7.5 | J6: 8.5 | K6: 9.5
A7: Discount factor | B7: =1/(1+WACC!$B$10)^B6 | C7: =1/(1+WACC!$B$10)^C6 | D7: =1/(1+WACC!$B$10)^D6 | E7: =1/(1+WACC!$B$10)^E6 | F7: =1/(1+WACC!$B$10)^F6 | G7: =1/(1+WACC!$B$10)^G6 | H7: =1/(1+WACC!$B$10)^H6 | I7: =1/(1+WACC!$B$10)^I6 | ... K7: =1/(1+WACC!$B$10)^K6
A8: PV of FCFF | B8: =B5*B7 | C8: =C5*C7 | D8: =D5*D7 | E8: =E5*E7 | F8: =F5*F7 | G8: =G5*G7 | H8: =H5*H7 | I8: =I5*I7 | ... K8: =K5*K7
A10: PV of explicit FCFF | B10: =SUM(B8:K8)
A11: Terminal NOPAT (FYn) | B11: =Model!O11
A12: Invested capital (mm) | B12: 37500
A13: Terminal invested capital (scaled w/ revenue) | B13: =$B$12*Model!O5/Model!E5
A14: Terminal ROIC | B14: =MAX($B$11/$B$13,WACC!$B$10)
A15: Terminal reinvestment rate (g/ROIC) | B15: =Assumptions!$B$22/$B$14
A16: Terminal value (Gordon) | B16: =$B$11*(1+Assumptions!$B$22)*(1-$B$15)/(WACC!$B$10-Assumptions!$B$22)
A17: PV of terminal value | B17: =$B$16/(1+WACC!$B$10)^(10-0.5)
A18: TV as % of EV | B18: =$B$17/($B$10+$B$17)
A20: Enterprise value | B20: =$B$10+$B$17
A21: (−) Net debt | B21: =-Assumptions!$B$10
A22: (−) Minority interest | B22: =-Assumptions!$B$9
A23: Equity value | B23: =$B$20-Assumptions!$B$10-Assumptions!$B$9
A24: Value per share | B24: =$B$23/Assumptions!$B$6
A25: Upside vs price | B25: =$B$24/Assumptions!$B$5-1

Sheet Sensitivity
A1: Value per share — WACC × terminal growth (USD/share)
A2: Every cell is a live formula; it re-runs the full DCF at that WACC/g pair.
A4: WACC \ g | B4: 0.015 | C4: 0.02 | D4: 0.025 | E4: 0.03 | F4: 0.035
A5: 0.076041291 | B5: =(SUMPRODUCT(DCF!$B$5:$K$5,1/(1+$A$5)^DCF!$B$6:$K$6)+DCF!$B$11*(1+B$4)*(1-B$4/DCF!$B$14)/($A$5-B$4)/(1+$A$5)^(10-0.5)-Assumptions!$B$10-Assumptions!$B$9)/Assumptions!$B$6 | C5: =(SUMPRODUCT(DCF!$B$5:$K$5,1/(1+$A$5)^DCF!$B$6:$K$6)+DCF!$B$11*(1+C$4)*(1-C$4/DCF!$B$14)/($A$5-C$4)/(1+$A$5)^(10-0.5)-Assumptions!$B$10-Assumptions!$B$9)/Assumptions!$B$6 | D5: =(SUMPRODUCT(DCF!$B$5:$K$5,1/(1+$A$5)^DCF!$B$6:$K$6)+DCF!$B$11*(1+D$4)*(1-D$4/DCF!$B$14)/($A$5-D$4)/(1+$A$5)^(10-0.5)-Assumptions!$B$10-Assumptions!$B$9)/Assumptions!$B$6 | E5: =(SUMPRODUCT(DCF!$B$5:$K$5,1/(1+$A$5)^DCF!$B$6:$K$6)+DCF!$B$11*(1+E$4)*(1-E$4/DCF!$B$14)/($A$5-E$4)/(1+$A$5)^(10-0.5)-Assumptions!$B$10-Assumptions!$B$9)/Assumptions!$B$6 | F5: =(SUMPRODUCT(DCF!$B$5:$K$5,1/(1+$A$5)^DCF!$B$6:$K$6)+DCF!$B$11*(1+F$4)*(1-F$4/DCF!$B$14)/($A$5-F$4)/(1+$A$5)^(10-0.5)-Assumptions!$B$10-Assumptions!$B$9)/Assumptions!$B$6
A6: 0.083541291 | B6: =(SUMPRODUCT(DCF!$B$5:$K$5,1/(1+$A$6)^DCF!$B$6:$K$6)+DCF!$B$11*(1+B$4)*(1-B$4/DCF!$B$14)/($A$6-B$4)/(1+$A$6)^(10-0.5)-Assumptions!$B$10-Assumptions!$B$9)/Assumptions!$B$6 | C6: =(SUMPRODUCT(DCF!$B$5:$K$5,1/(1+$A$6)^DCF!$B$6:$K$6)+DCF!$B$11*(1+C$4)*(1-C$4/DCF!$B$14)/($A$6-C$4)/(1+$A$6)^(10-0.5)-Assumptions!$B$10-Assumptions!$B$9)/Assumptions!$B$6 | D6: =(SUMPRODUCT(DCF!$B$5:$K$5,1/(1+$A$6)^DCF!$B$6:$K$6)+DCF!$B$11*(1+D$4)*(1-D$4/DCF!$B$14)/($A$6-D$4)/(1+$A$6)^(10-0.5)-Assumptions!$B$10-Assumptions!$B$9)/Assumptions!$B$6 | E6: =(SUMPRODUCT(DCF!$B$5:$K$5,1/(1+$A$6)^DCF!$B$6:$K$6)+DCF!$B$11*(1+E$4)*(1-E$4/DCF!$B$14)/($A$6-E$4)/(1+$A$6)^(10-0.5)-Assumptions!$B$10-Assumptions!$B$9)/Assumptions!$B$6 | F6: =(SUMPRODUCT(DCF!$B$5:$K$5,1/(1+$A$6)^DCF!$B$6:$K$6)+DCF!$B$11*(1+F$4)*(1-F$4/DCF!$B$14)/($A$6-F$4)/(1+$A$6)^(10-0.5)-Assumptions!$B$10-Assumptions!$B$9)/Assumptions!$B$6
A7: 0.091041291 | B7: =(SUMPRODUCT(DCF!$B$5:$K$5,1/(1+$A$7)^DCF!$B$6:$K$6)+DCF!$B$11*(1+B$4)*(1-B$4/DCF!$B$14)/($A$7-B$4)/(1+$A$7)^(10-0.5)-Assumptions!$B$10-Assumptions!$B$9)/Assumptions!$B$6 | C7: =(SUMPRODUCT(DCF!$B$5:$K$5,1/(1+$A$7)^DCF!$B$6:$K$6)+DCF!$B$11*(1+C$4)*(1-C$4/DCF!$B$14)/($A$7-C$4)/(1+$A$7)^(10-0.5)-Assumptions!$B$10-Assumptions!$B$9)/Assumptions!$B$6 | D7: =(SUMPRODUCT(DCF!$B$5:$K$5,1/(1+$A$7)^DCF!$B$6:$K$6)+DCF!$B$11*(1+D$4)*(1-D$4/DCF!$B$14)/($A$7-D$4)/(1+$A$7)^(10-0.5)-Assumptions!$B$10-Assumptions!$B$9)/Assumptions!$B$6 | E7: =(SUMPRODUCT(DCF!$B$5:$K$5,1/(1+$A$7)^DCF!$B$6:$K$6)+DCF!$B$11*(1+E$4)*(1-E$4/DCF!$B$14)/($A$7-E$4)/(1+$A$7)^(10-0.5)-Assumptions!$B$10-Assumptions!$B$9)/Assumptions!$B$6 | F7: =(SUMPRODUCT(DCF!$B$5:$K$5,1/(1+$A$7)^DCF!$B$6:$K$6)+DCF!$B$11*(1+F$4)*(1-F$4/DCF!$B$14)/($A$7-F$4)/(1+$A$7)^(10-0.5)-Assumptions!$B$10-Assumptions!$B$9)/Assumptions!$B$6
A8: 0.098541291 | B8: =(SUMPRODUCT(DCF!$B$5:$K$5,1/(1+$A$8)^DCF!$B$6:$K$6)+DCF!$B$11*(1+B$4)*(1-B$4/DCF!$B$14)/($A$8-B$4)/(1+$A$8)^(10-0.5)-Assumptions!$B$10-Assumptions!$B$9)/Assumptions!$B$6 | C8: =(SUMPRODUCT(DCF!$B$5:$K$5,1/(1+$A$8)^DCF!$B$6:$K$6)+DCF!$B$11*(1+C$4)*(1-C$4/DCF!$B$14)/($A$8-C$4)/(1+$A$8)^(10-0.5)-Assumptions!$B$10-Assumptions!$B$9)/Assumptions!$B$6 | D8: =(SUMPRODUCT(DCF!$B$5:$K$5,1/(1+$A$8)^DCF!$B$6:$K$6)+DCF!$B$11*(1+D$4)*(1-D$4/DCF!$B$14)/($A$8-D$4)/(1+$A$8)^(10-0.5)-Assumptions!$B$10-Assumptions!$B$9)/Assumptions!$B$6 | E8: =(SUMPRODUCT(DCF!$B$5:$K$5,1/(1+$A$8)^DCF!$B$6:$K$6)+DCF!$B$11*(1+E$4)*(1-E$4/DCF!$B$14)/($A$8-E$4)/(1+$A$8)^(10-0.5)-Assumptions!$B$10-Assumptions!$B$9)/Assumptions!$B$6 | F8: =(SUMPRODUCT(DCF!$B$5:$K$5,1/(1+$A$8)^DCF!$B$6:$K$6)+DCF!$B$11*(1+F$4)*(1-F$4/DCF!$B$14)/($A$8-F$4)/(1+$A$8)^(10-0.5)-Assumptions!$B$10-Assumptions!$B$9)/Assumptions!$B$6
A9: 0.10604129 | B9: =(SUMPRODUCT(DCF!$B$5:$K$5,1/(1+$A$9)^DCF!$B$6:$K$6)+DCF!$B$11*(1+B$4)*(1-B$4/DCF!$B$14)/($A$9-B$4)/(1+$A$9)^(10-0.5)-Assumptions!$B$10-Assumptions!$B$9)/Assumptions!$B$6 | C9: =(SUMPRODUCT(DCF!$B$5:$K$5,1/(1+$A$9)^DCF!$B$6:$K$6)+DCF!$B$11*(1+C$4)*(1-C$4/DCF!$B$14)/($A$9-C$4)/(1+$A$9)^(10-0.5)-Assumptions!$B$10-Assumptions!$B$9)/Assumptions!$B$6 | D9: =(SUMPRODUCT(DCF!$B$5:$K$5,1/(1+$A$9)^DCF!$B$6:$K$6)+DCF!$B$11*(1+D$4)*(1-D$4/DCF!$B$14)/($A$9-D$4)/(1+$A$9)^(10-0.5)-Assumptions!$B$10-Assumptions!$B$9)/Assumptions!$B$6 | E9: =(SUMPRODUCT(DCF!$B$5:$K$5,1/(1+$A$9)^DCF!$B$6:$K$6)+DCF!$B$11*(1+E$4)*(1-E$4/DCF!$B$14)/($A$9-E$4)/(1+$A$9)^(10-0.5)-Assumptions!$B$10-Assumptions!$B$9)/Assumptions!$B$6 | F9: =(SUMPRODUCT(DCF!$B$5:$K$5,1/(1+$A$9)^DCF!$B$6:$K$6)+DCF!$B$11*(1+F$4)*(1-F$4/DCF!$B$14)/($A$9-F$4)/(1+$A$9)^(10-0.5)-Assumptions!$B$10-Assumptions!$B$9)/Assumptions!$B$6

Sheet Comps
A1: Comparable companies
A2: Peer inputs in blue; medians and implied values are live formulas.
A4: Peer | B4: EV/EBITDA | C4: EV/EBIT | D4: EV/Sales | E4: P/E
A5: PEERA | B5: 17.666667 | C5: 22.649573 | D5: 2.5645161 | E5: 23.870968
A6: PEERB | B6: 16.721311 | C6: 21.437579 | D6: 2.4878049 | E6: 23.72549
A7: PEERC | B7: 17.12 | C7: 21.948718 | D7: 2.7435897 | E7: 29.438202
A8: PEERD | B8: 16.666667 | C8: 21.367521 | D8: 2.4242424 | E8: 20.952381
A9: PEERE | B9: 16.829268 | C9: 21.575985 | D9: 2.5090909 | E9: 23.783784
A10: Median | B10: =MEDIAN(B5:B9) | C10: =MEDIAN(C5:C9) | D10: =MEDIAN(D5:D9) | E10: =MEDIAN(E5:E9)
A12: Company metric | B12: Value | C12: ×median | D12: Implied VPS (USD)
A13: EBITDA | B13: 28968.151 | C13: =B10 | D13: =(B13*C13-Assumptions!$B$10-Assumptions!$B$9)/Assumptions!$B$6
A14: EBIT | B14: 24498.288 | C14: =C10 | D14: =(B14*C14-Assumptions!$B$10-Assumptions!$B$9)/Assumptions!$B$6
A15: Revenue | B15: 85958.904 | C15: =D10 | D15: =(B15*C15-Assumptions!$B$10-Assumptions!$B$9)/Assumptions!$B$6
A16: EPS | B16: 12.868495 | C16: =E10 | D16: =B16*C16

Sheet IS (reported)
A1: DEMO — IS (reported)
A2: As reported by DEMO (synthetic) (USDmm). Hardcoded actuals.
A4: Line item | B4: FY2020 | C4: FY2021 | D4: FY2022 | E4: FY2023 | F4: FY2024 | G4: FY2025
A5: Revenue | B5: 58000 | C5: 64380 | D5: 70174.2 | E5: 75086.394 | F5: 81093.306 | G5: 85958.904
A6: EBIT (operating income) | B6: 15080 | C6: 17060.7 | D6: 18947.034 | E6: 20648.758 | F6: 22706.126 | G6: 24498.288
A7: EBITDA | B7: 18096 | C7: 20408.46 | D7: 22596.092 | E7: 24553.251 | F7: 26922.977 | G7: 28968.151
A8: D&A | B8: 3016 | C8: 3347.76 | D8: 3649.0584 | E8: 3904.4925 | F8: 4216.8519 | G8: 4469.863
A9: Interest expense | B9: 550 | C9: 550 | D9: 550 | E9: 550 | F9: 550 | G9: 550
A10: Pre-tax income | B10: 14730 | C10: 16710.7 | D10: 18597.034 | E10: 20298.758 | F10: 22356.126 | G10: 24148.288
A11: Tax expense | B11: 2798.7 | C11: 3175.033 | D11: 3533.4365 | E11: 3856.7641 | F11: 4247.6639 | G11: 4588.1746
A12: Net income | B12: 11931.3 | C12: 13535.667 | D12: 15063.598 | E12: 16441.994 | F12: 18108.462 | G12: 19560.113

Sheet BS (reported)
A1: DEMO — BS (reported)
A2: As reported by DEMO (synthetic) (USDmm). Hardcoded actuals.
A4: Line item | B4: FY2020 | C4: FY2021 | D4: FY2022 | E4: FY2023 | F4: FY2024 | G4: FY2025
A5: Total debt | B5: 12000 | C5: 12000 | D5: 12000 | E5: 12000 | F5: 12000 | G5: 12000
A6: Cash & ST investments | B6: 9500 | C6: 10100 | D6: 10700 | E6: 11300 | F6: 11900 | G6: 12500
A7: Total equity | B7: 28000 | C7: 30000 | D7: 32000 | E7: 34000 | F7: 36000 | G7: 38000
A8: Minority interest | B8: 300 | C8: 300 | D8: 300 | E8: 300 | F8: 300 | G8: 300

Sheet CF (reported)
A1: DEMO — CF (reported)
A2: As reported by DEMO (synthetic) (USDmm). Hardcoded actuals.
A4: Line item | B4: FY2020 | C4: FY2021 | D4: FY2022 | E4: FY2023 | F4: FY2024 | G4: FY2025
A5: Operating cash flow | B5: 14947.3 | C5: 16883.427 | D5: 18712.656 | E5: 20346.487 | F5: 22325.314 | G5: 24029.976
A6: Capex | B6: 2784 | C6: 3090.24 | D6: 3368.3616 | E6: 3604.1469 | F6: 3892.4787 | G6: 4126.0274
A7: Change in NWC | B7: 696 | C7: 772.56 | D7: 842.0904 | E7: 901.03673 | F7: 973.11967 | G7: 1031.5068
